maxdmg_resource/__init__.py
maxdmg_resource/app/API.py
maxdmg_resource/app/Config.py
maxdmg_resource/app/Exceptions.py
maxdmg_resource/app/Graph.py
maxdmg_resource/app/Loader/Errors.py
maxdmg_resource/app/Loader/Loader.py
maxdmg_resource/app/Loader/Models.py
maxdmg_resource/app/Loader/__init__.py
maxdmg_resource/app/Types/Doc.py
maxdmg_resource/app/Types/Form.py
maxdmg_resource/app/Types/State.py
maxdmg_resource/app/Types/Transition.py
maxdmg_resource/app/Types/Typedefs.py
maxdmg_resource/app/Types/__init__.py
maxdmg_resource-0.0.3.dist-info/METADATA
maxdmg_resource-0.0.3.dist-info/WHEEL
maxdmg_resource-0.0.3.dist-info/top_level.txt
maxdmg_resource-0.0.3.dist-info/RECORD
