Metadata-Version: 2.1
Name: maxdmg-resource
Version: 0.0.3
Summary: This is a resource loader for maxdmg project.
Author: tonotonokon
Classifier: Programming Language :: Python :: 3
Classifier: License :: OSI Approved :: MIT License
Classifier: Operating System :: OS Independent
Requires-Python: >=3.10
Requires-Dist: python-dotenv (==1.0.0)
Requires-Dist: pyairtable (==1.4.0)
